minchin/pelican/plugins/static_comments/__init__.py
minchin/pelican/plugins/static_comments/avatars.py
minchin/pelican/plugins/static_comments/comment.py
minchin/pelican/plugins/static_comments/identicon/__init__.py
minchin/pelican/plugins/static_comments/identicon/identicon.py
minchin/pelican/plugins/static_comments/import/__init__.py
minchin/pelican/plugins/static_comments/import/blogger_comment_export.py
minchin.pelican.plugins.static_comments-2.1.2.dist-info/COPYING
minchin.pelican.plugins.static_comments-2.1.2.dist-info/LICENSE.txt
minchin.pelican.plugins.static_comments-2.1.2.dist-info/METADATA
minchin.pelican.plugins.static_comments-2.1.2.dist-info/WHEEL
minchin.pelican.plugins.static_comments-2.1.2.dist-info/entry_points.txt
minchin.pelican.plugins.static_comments-2.1.2.dist-info/top_level.txt
minchin.pelican.plugins.static_comments-2.1.2.dist-info/RECORD
