Metadata-Version: 2.1
Name: minchin.pelican.plugins.static-comments
Version: 2.1.2
Summary: A Pelican plugin, which allows you to add static comments to your articles.
Home-page: https://github.com/MinchinWeb/minchin.pelican.plugins.static_comments
Author: William Minchin
Author-email: w_minchin@hotmail.com
License: GPLv3+
Platform: any
Classifier: Development Status :: 5 - Production/Stable
Classifier: Programming Language :: Python :: 3
Classifier: Programming Language :: Python :: 3.7
Classifier: Programming Language :: Python :: 3.8
Classifier: Programming Language :: Python :: 3.9
Classifier: Programming Language :: Python :: 3.10
Classifier: Environment :: Console
Classifier: Framework :: Pelican :: Plugins
Classifier: License :: OSI Approved :: GNU General Public License v3 or later (GPLv3+)
Classifier: Operating System :: OS Independent
Classifier: Topic :: Software Development :: Libraries :: Python Modules
License-File: LICENSE.txt
License-File: COPYING
Requires-Dist: minchin.pelican.plugins.autoloader !=1.2.0
Requires-Dist: pelican >=3.4
Requires-Dist: pillow
Provides-Extra: all
Requires-Dist: minchin.releaser ; extra == 'all'
Requires-Dist: pip-tools ; extra == 'all'
Requires-Dist: untangle ; extra == 'all'
Provides-Extra: blogger
Requires-Dist: untangle ; extra == 'blogger'
Provides-Extra: build
Requires-Dist: minchin.releaser ; extra == 'build'
Requires-Dist: pip-tools ; extra == 'build'
Provides-Extra: docs
Provides-Extra: test
